{
  "type": "minecraft:crafting_shapeless",
  "category": "equipment",
  "ingredients": [
    [
      {
        "type": "neoforge:components",
        "components": {
          "minecraft:potion_contents": {
            "potion": "minecraft:strength"
          }
        },
        "items": "minecraft:potion"
      },
      {
        "type": "neoforge:components",
        "components": {
          "minecraft:potion_contents": {
            "potion": "minecraft:long_strength"
          }
        },
        "items": "minecraft:potion"
      },
      {
        "type": "neoforge:components",
        "components": {
          "minecraft:potion_contents": {
            "potion": "minecraft:strong_strength"
          }
        },
        "items": "minecraft:potion"
      }
    ],
    {
      "type": "neoforge:components",
      "components": {
        "minecraft:damage": 9
      },
      "items": "twilightforest:zombie_scepter"
    },
    {
      "item": "minecraft:rotten_flesh"
    }
  ],
  "result": {
    "count": 1,
    "id": "twilightforest:zombie_scepter"
  }
}